main.py
tremeschin-0.1.0.dist-info/METADATA
tremeschin-0.1.0.dist-info/WHEEL
tremeschin-0.1.0.dist-info/top_level.txt
tremeschin-0.1.0.dist-info/RECORD
