Metadata-Version: 2.4
Name: tremeschin
Version: 0.1.0
Summary: Hey, that is my username!
Requires-Python: >=3.13
